README.md
setup.py
iotex_etl.egg-info/PKG-INFO
iotex_etl.egg-info/SOURCES.txt
iotex_etl.egg-info/dependency_links.txt
iotex_etl.egg-info/entry_points.txt
iotex_etl.egg-info/requires.txt
iotex_etl.egg-info/top_level.txt
iotexetl/__init__.py
iotexetl/__main__.py
iotexetl/cli/__init__.py
iotexetl/cli/export_blocks.py
iotexetl/cli/export_transaction_logs.py
iotexetl/cli/get_block_range_for_date.py
iotexetl/cli/stream.py
iotexetl/enumeration/__init__.py
iotexetl/enumeration/entity_type.py
iotexetl/exporters/__init__.py
iotexetl/exporters/iotex_item_exporter.py
iotexetl/jobs/__init__.py
iotexetl/jobs/export_blocks_job.py
iotexetl/jobs/export_transaction_logs_job.py
iotexetl/mappers/__init__.py
iotexetl/mappers/action_mapper.py
iotexetl/mappers/block_mapper.py
iotexetl/mappers/log_mapper.py
iotexetl/mappers/receipt_mapper.py
iotexetl/mappers/transaction_log_mapper.py
iotexetl/rpc/__init__.py
iotexetl/rpc/iotex_rpc.py
iotexetl/rpc/iotexapi/__init__.py
iotexetl/rpc/iotexapi/api_pb2.py
iotexetl/rpc/iotexapi/api_pb2_grpc.py
iotexetl/rpc/iotextypes/__init__.py
iotexetl/rpc/iotextypes/action_pb2.py
iotexetl/rpc/iotextypes/action_pb2_grpc.py
iotexetl/rpc/iotextypes/blockchain_pb2.py
iotexetl/rpc/iotextypes/blockchain_pb2_grpc.py
iotexetl/rpc/iotextypes/election_pb2.py
iotexetl/rpc/iotextypes/election_pb2_grpc.py
iotexetl/rpc/iotextypes/endorsement_pb2.py
iotexetl/rpc/iotextypes/endorsement_pb2_grpc.py
iotexetl/rpc/iotextypes/node_pb2.py
iotexetl/rpc/iotextypes/node_pb2_grpc.py
iotexetl/rpc/iotextypes/transaction_log_pb2.py
iotexetl/rpc/iotextypes/transaction_log_pb2_grpc.py
iotexetl/service/__init__.py
iotexetl/service/iotex_block_range_service.py
iotexetl/service/iotex_block_timestamp_graph.py
iotexetl/service/iotex_service.py
iotexetl/streaming/__init__.py
iotexetl/streaming/iotex_streamer_adapter.py
iotexetl/streaming/item_exporter_creator.py
iotexetl/streaming/item_id_calculator.py
iotexetl/utils/__init__.py
iotexetl/utils/iotex_utils.py
iotexetl/utils/string_utils.py
tests/iotexetl/__init__.py
tests/iotexetl/helpers.py
tests/iotexetl/mock_iotex_rpc.py
tests/resources/__init__.py