Metadata-Version: 2.1
Name: iotex-etl
Version: 1.0.2
Summary: Tools for exporting IoTeX blockchain data to JSON
Home-page: https://github.com/blockchain-etl/iotex-etl
Author: Evgeny Medvedev
Author-email: evge.medvedev@gmail.com
License: UNKNOWN
Project-URL: Bug Reports, https://github.com/blockchain-etl/iotex-etl/issues
Project-URL: Source, https://github.com/blockchain-etl/iotex-etl
Keywords: IoTeX
Platform: UNKNOWN
Classifier: Development Status :: 5 - Production/Stable
Classifier: Intended Audience :: Developers
Classifier: License :: OSI Approved :: MIT License
Classifier: Programming Language :: Python :: 3
Classifier: Programming Language :: Python :: 3.6
Classifier: Programming Language :: Python :: 3.7
Requires-Python: >=3.6.0,<3.8.0
Provides-Extra: streaming
Provides-Extra: dev
